[
 {
  "geoId": "BAE72B3C-3BE4-4F1F-958D-6601111C30C9",
  "type": "weekly",
  "isPrimary": 1,
  "location": {
   "latitude": 42.968964,
   "longitude": 144.070079,
   "iso": "JPN"
  },
  "properties": {
   "orgName": "北海道白糠町白糠",
   "orgType": "CONG",
   "orgTransliteratedName": "HOKKAIDO SHIRANUKACHO SHIRANUKA",
   "address": "0880331\n北海道白糠郡白糠町東一条北9丁目2番地19",
   "transliteratedAddress": "0880331\r\n9-2-19 Higashiichijokita,Shiranuka-gun shiranuka-cho, Hokkaido\r\n\r\n",
   "languageCode": "J",
   "schedule": "Sun 10:00 Thu 19:00",
   "phones": [ "0154725761" ],
   "isPrivateMtgPlace": 0
  },
  "lastVisit": "2023-12-27",
  "lastSeen": "2023-12-27",
  "active": 1,
  "firstSeen": "2022-12-02"
 },
 {
  "geoId": "7B02E7A2-745D-4905-8C62-4F6372F00267",
  "type": "weekly",
  "isPrimary": 1,
  "location": {
   "latitude": 43.003277,
   "longitude": 144.343053,
   "iso": "JPN"
  },
  "properties": {
   "orgName": "北海道釧路市文苑",
   "orgType": "CONG",
   "orgTransliteratedName": "HOKKAIDO KUSHIROSHI FUMIZONO",
   "address": "0840904\n北海道釧路市新富士町5-6-6",
   "transliteratedAddress": "0840904\r\n5-6-6 Shinfuji-cho, Kushiro-shi, Hokkaido\r\n\r\n",
   "languageCode": "J",
   "schedule": "Sun 13:30 Thu 19:00",
   "phones": [ "050 3702 8971" ],
   "isPrivateMtgPlace": 0
  },
  "lastVisit": "2023-12-27",
  "lastSeen": "2023-12-27",
  "active": 1,
  "firstSeen": "2022-12-02"
 },
 {
  "geoId": "72A2C8A8-EE3E-41EF-BEF0-F8EB66935AC0",
  "type": "weekly",
  "isPrimary": 1,
  "location": {
   "latitude": 43.003277,
   "longitude": 144.343053,
   "iso": "JPN"
  },
  "properties": {
   "orgName": "北海道釧路市新富士",
   "orgType": "CONG",
   "orgTransliteratedName": "HOKKAIDO KUSHIROSHI SHINFUJI",
   "address": "0840904\n北海道釧路市新富士町5-6-6",
   "transliteratedAddress": "0840904\r\n5-6-6 Shinfuji-cho, Kushiro-shi, Hokkaido\r\n\r\n",
   "languageCode": "J",
   "schedule": "Sun 10:00 Wed 19:00",
   "phones": [ "080-2294-9530" ],
   "isPrivateMtgPlace": 0
  },
  "lastVisit": "2023-12-27",
  "lastSeen": "2023-12-27",
  "active": 1,
  "firstSeen": "2022-12-02"
 },
 {
  "geoId": "27AECD1E-3DF6-49B1-BC13-60482937A6DD",
  "type": "weekly",
  "isPrimary": 1,
  "location": {
   "latitude": 42.99326,
   "longitude": 144.394777,
   "iso": "JPN"
  },
  "properties": {
   "orgName": "北海道釧路市幣舞",
   "orgType": "CONG",
   "orgTransliteratedName": "HOKKAIDO KUSHIROSHI NUSAMAI",
   "address": "0850003\n北海道釧路市川北町7-21",
   "transliteratedAddress": "0850003\r\n7-21 Kawakita-cho, Kushiro-shi, Hokkaido\r\n\r\n",
   "languageCode": "J",
   "schedule": "Sat 18:30 Wed 19:00",
   "phones": [ "080-8712-9081" ],
   "isPrivateMtgPlace": 0
  },
  "lastVisit": "2023-12-27",
  "lastSeen": "2023-12-27",
  "active": 1,
  "firstSeen": "2022-12-02"
 },
 {
  "geoId": "4DEC83B8-4D17-46BE-94E9-DC9DE8B4C6D8",
  "type": "weekly",
  "isPrimary": 1,
  "location": {
   "latitude": 42.99326,
   "longitude": 144.394777,
   "iso": "JPN"
  },
  "properties": {
   "orgName": "北海道釧路市花園",
   "orgType": "CONG",
   "orgTransliteratedName": "HOKKAIDO KUSHIROSHI HANAZONO",
   "address": "0850003\n北海道釧路市川北町7-21",
   "transliteratedAddress": "0850003\r\n7-21 Kawakita-cho, Kushiro-shi, Hokkaido\r\n\r\n",
   "languageCode": "J",
   "schedule": "Sun 14:00 Thu 19:00",
   "phones": [ "080-9994-7672" ],
   "isPrivateMtgPlace": 0
  },
  "lastVisit": "2023-12-27",
  "lastSeen": "2023-12-27",
  "active": 1,
  "firstSeen": "2022-12-02"
 },
 {
  "geoId": "FA8E9500-6654-4F09-8F2D-D5EC3294F03F",
  "type": "weekly",
  "isPrimary": 1,
  "location": {
   "latitude": 42.99326,
   "longitude": 144.394777,
   "iso": "JPN"
  },
  "properties": {
   "orgName": "北海道釧路市鶴ケ岱",
   "orgType": "CONG",
   "orgTransliteratedName": "HOKKAIDO KUSHIROSHI TSURUGADAI",
   "address": "0850003\n北海道釧路市川北町7-21",
   "transliteratedAddress": "0850003\r\n7-21 Kawakita-cho, Kushiro-shi, Hokkaido\r\n\r\n",
   "languageCode": "J",
   "schedule": "Sun 10:00 Fri 19:00",
   "phones": [ "080-7847-9678" ],
   "isPrivateMtgPlace": 0
  },
  "lastVisit": "2023-12-27",
  "lastSeen": "2023-12-27",
  "active": 1,
  "firstSeen": "2022-12-02"
 },
 {
  "geoId": "BC5A263E-510F-4933-B666-4989DB4D0501",
  "type": "weekly",
  "isPrimary": 1,
  "location": {
   "latitude": 43.076998,
   "longitude": 144.81456,
   "iso": "JPN"
  },
  "properties": {
   "orgName": "北海道厚岸町厚岸",
   "orgType": "CONG",
   "orgTransliteratedName": "HOKKAIDO AKKESHICHO AKKESHI",
   "address": "0881129\n北海道厚岸郡厚岸町光栄269",
   "transliteratedAddress": "0881129\r\n269 Koei, Akkeshi-cho Akkeshi-gun, Hokkaido\r\n\r\n",
   "languageCode": "J",
   "schedule": "Sun 10:00 Thu 19:00",
   "phones": [ "080ー8391－8516" ],
   "isPrivateMtgPlace": 0
  },
  "lastVisit": "2023-12-27",
  "lastSeen": "2023-12-27",
  "active": 1,
  "firstSeen": "2022-12-02"
 },
 {
  "geoId": "3EF8333F-6405-45E5-9617-05DC9640BE22",
  "type": "weekly",
  "isPrimary": 1,
  "location": {
   "latitude": 43.323145,
   "longitude": 144.612469,
   "iso": "JPN"
  },
  "properties": {
   "orgName": "北海道標茶町標茶",
   "orgType": "CONG",
   "orgTransliteratedName": "HOKKAIDO SHIBECHACHO SHIBECHA",
   "address": "0882339\n北海道川上郡標茶町多和375-7",
   "transliteratedAddress": "0882339\r\n375-7 Tawa, Kawakami-gun shibecha-cho, Hokkaido\r\n\r\n",
   "languageCode": "J",
   "schedule": "Sun 10:00 Thu 19:00",
   "phones": [ "015-485-1775" ],
   "isPrivateMtgPlace": 0
  },
  "lastVisit": "2023-12-27",
  "lastSeen": "2023-12-27",
  "active": 1,
  "firstSeen": "2022-12-02"
 },
 {
  "geoId": "334A4C88-E688-410D-B153-48421C32965D",
  "type": "weekly",
  "isPrimary": 1,
  "location": {
   "latitude": 43.825556,
   "longitude": 144.11251,
   "iso": "JPN"
  },
  "properties": {
   "orgName": "北海道美幌町美幌",
   "orgType": "CONG",
   "orgTransliteratedName": "HOKKAIDO BIHOROCHO BIHORO",
   "address": "0920067\n北海道網走郡美幌町字三橋南9-16",
   "transliteratedAddress": "0920067\r\nHOKKAIDO ABASHIRI-GUNBIHORO-CHOMIHASHIMINAMI 9-16\r\n\r\n",
   "languageCode": "J",
   "schedule": "Sun 10:00 Thu 19:00",
   "phones": [ "0152-72-3384" ],
   "isPrivateMtgPlace": 0
  },
  "lastVisit": "2023-12-27",
  "lastSeen": "2023-12-27",
  "active": 1,
  "firstSeen": "2022-12-02"
 },
 {
  "geoId": "1B0D6049-3224-4FB5-A326-06495ED33A65",
  "type": "weekly",
  "isPrimary": 1,
  "location": {
   "latitude": 44.003157,
   "longitude": 144.266697,
   "iso": "JPN"
  },
  "properties": {
   "orgName": "北海道網走市網走",
   "orgType": "CONG",
   "orgTransliteratedName": "HOKKAIDO ABASHIRISHI ABASHIRI",
   "address": "0930042\n北海道網走市潮見3-12-2",
   "transliteratedAddress": "0930042\r\n3-12ー2 Shiomi, Abashiri-shi, Hokkaido\r\n\r\n",
   "languageCode": "J",
   "schedule": "Sun 10:00 Thu 19:00",
   "phones": [ "0152-45-0748" ],
   "isPrivateMtgPlace": 0
  },
  "lastVisit": "2023-12-27",
  "lastSeen": "2023-12-27",
  "active": 1,
  "firstSeen": "2022-12-02"
 },
 {
  "geoId": "0B3C1E09-A192-40A4-84D7-46710FC964C4",
  "type": "weekly",
  "isPrimary": 1,
  "location": {
   "latitude": 43.568418,
   "longitude": 144.967326,
   "iso": "JPN"
  },
  "properties": {
   "orgName": "北海道中標津町中標津",
   "orgType": "CONG",
   "orgTransliteratedName": "HOKKAIDO NAKASHIBETSUCHO NAKASHIBETSU",
   "address": "0861145\n北海道標津郡中標津町北中1-15",
   "transliteratedAddress": "0861145\r\n1-15 Kitanaka, Shibetsu-gun nakashibetsu-cho,Hokkaido\r\n\r\n",
   "languageCode": "J",
   "schedule": "Sun 10:00 Thu 19:00",
   "phones": [ "0153-72-7712　　090-1302-5908" ],
   "isPrivateMtgPlace": 0
  },
  "lastVisit": "2023-12-27",
  "lastSeen": "2023-12-27",
  "active": 1,
  "firstSeen": "2022-12-02"
 },
 {
  "geoId": "7EF8A2C6-A051-4BD1-9F4A-DE93E5E390FB",
  "type": "weekly",
  "isPrimary": 1,
  "location": {
   "latitude": 43.899913,
   "longitude": 144.683166,
   "iso": "JPN"
  },
  "properties": {
   "orgName": "北海道斜里町斜里",
   "orgType": "CONG",
   "orgTransliteratedName": "HOKKAIDO SHARICHO SHARI",
   "address": "0994141\n北海道斜里郡斜里町字豊倉70番地23",
   "transliteratedAddress": "0994141\r\n70-23 Aza-toyokura, Shari-gun shari-cho, Hokkaido\r\n\r\n",
   "languageCode": "J",
   "schedule": "Sun 10:00 Thu 19:00",
   "phones": [ "0152-23-3424" ],
   "isPrivateMtgPlace": 0
  },
  "lastVisit": "2023-12-27",
  "lastSeen": "2023-12-27",
  "active": 1,
  "firstSeen": "2022-12-02"
 },
 {
  "geoId": "965577B6-B258-4469-97C2-1B74434CE4F3",
  "type": "weekly",
  "isPrimary": 1,
  "location": {
   "latitude": 43.332372,
   "longitude": 145.592923,
   "iso": "RUS"
  },
  "properties": {
   "orgName": "北海道根室市根室",
   "orgType": "CONG",
   "orgTransliteratedName": "HOKKAIDO NEMUROSHI NEMURO",
   "address": "0870006\n北海道根室市曙町1-42",
   "transliteratedAddress": "0870006\r\n1-42 Akebono-cho, Nemuro-shi, Hokkaido\r\n\r\n",
   "languageCode": "J",
   "schedule": "Sun 10:00 Thu 19:00",
   "phones": [ "0153-24-8049" ],
   "isPrivateMtgPlace": 0
  },
  "lastVisit": "2023-12-27",
  "lastSeen": "2023-12-27",
  "active": 1,
  "firstSeen": "2022-12-02"
 }
]